[
  {
    "step": 1,
    "bgColor": "bg-blue-600",
    "title": "Step 1: A1 & A2 Levels",
    "points": [
      "<25%: Fail (No retake)",
      "25-49.99%: A1 Certified",
      "50-74.99%: A2 Certified",
      "≥75%: A2 + Proceed to Step 2"
    ]
  },
  {
    "step": 2,
    "bgColor": "bg-green-600",
    "title": "Step 2: B1 & B2 Levels",
    "points": [
      "<25%: Remain at A2",
      "25-49.99%: B1 Certified",
      "50-74.99%: B2 Certified",
      "≥75%: B2 + Proceed to Step 3"
    ]
  },
  {
    "step": 3,
    "bgColor": "bg-purple-600",
    "title": "Step 3: C1 & C2 Levels",
    "points": [
      "<25%: Remain at B2",
      "25-49.99%: C1 Certified",
      "≥50%: C2 Certified"
    ]
  }
]
